prompto/__init__.py
prompto/apis/__init__.py
prompto/apis/anthropic/__init__.py
prompto/apis/anthropic/anthropic.py
prompto/apis/anthropic/anthropic_utils.py
prompto/apis/azure_openai/__init__.py
prompto/apis/azure_openai/azure_openai.py
prompto/apis/base.py
prompto/apis/gemini/__init__.py
prompto/apis/gemini/gemini.py
prompto/apis/gemini/gemini_utils.py
prompto/apis/huggingface_tgi/__init__.py
prompto/apis/huggingface_tgi/huggingface_tgi.py
prompto/apis/ollama/__init__.py
prompto/apis/ollama/ollama.py
prompto/apis/ollama/ollama_utils.py
prompto/apis/openai/__init__.py
prompto/apis/openai/openai.py
prompto/apis/openai/openai_utils.py
prompto/apis/quart/__init__.py
prompto/apis/quart/quart.py
prompto/apis/quart/quart_api.py
prompto/apis/quart/quart_utils.py
prompto/apis/testing/__init__.py
prompto/apis/testing/testing_api.py
prompto/apis/vertexai/__init__.py
prompto/apis/vertexai/vertexai.py
prompto/apis/vertexai/vertexai_utils.py
prompto/experiment.py
prompto/experiment_pipeline.py
prompto/judge.py
prompto/scorer.py
prompto/scripts/__init__.py
prompto/scripts/check_experiment.py
prompto/scripts/convert_images.py
prompto/scripts/create_judge_file.py
prompto/scripts/obtain_missing_id_jsonl.py
prompto/scripts/run_experiment.py
prompto/scripts/run_pipeline.py
prompto/settings.py
prompto/utils.py
prompto-0.2.1.dist-info/LICENSE.md
prompto-0.2.1.dist-info/METADATA
prompto-0.2.1.dist-info/WHEEL
prompto-0.2.1.dist-info/entry_points.txt
prompto-0.2.1.dist-info/RECORD
