Metadata-Version: 2.1
Name: prompto
Version: 0.2.1
Summary: Library for asynchronous querying of LLM API endpoints and logging progress
Author: rchan
Author-email: rchan@turing.ac.uk
Requires-Python: >=3.11,<4.0
Classifier: Programming Language :: Python :: 3
Classifier: Programming Language :: Python :: 3.11
Classifier: Programming Language :: Python :: 3.12
Classifier: Programming Language :: Python :: 3.13
Provides-Extra: all
Provides-Extra: anthropic
Provides-Extra: azure-openai
Provides-Extra: dev
Provides-Extra: gemini
Provides-Extra: huggingface-tgi
Provides-Extra: ollama
Provides-Extra: openai
Provides-Extra: quart
Provides-Extra: vertexai
Requires-Dist: accelerate (>=0.34.2,<0.35.0) ; extra == "all" or extra == "quart"
Requires-Dist: aiohttp (>=3.9.5,<4.0.0) ; extra == "all" or extra == "quart"
Requires-Dist: anthropic (>=0.31.1,<0.32.0) ; extra == "all" or extra == "anthropic"
Requires-Dist: black (>=24.3.0,<25.0.0) ; extra == "all" or extra == "dev"
Requires-Dist: cli-test-helpers (>=4.0.0,<5.0.0) ; extra == "all" or extra == "dev"
Requires-Dist: google-cloud-aiplatform (>=1.66.0,<2.0.0) ; extra == "all" or extra == "gemini" or extra == "vertexai"
Requires-Dist: google-generativeai (>=0.8.1,<0.9.0) ; extra == "all" or extra == "gemini" or extra == "vertexai"
Requires-Dist: huggingface-hub (>=0.23.4,<0.24.0) ; extra == "all" or extra == "huggingface-tgi"
Requires-Dist: ipykernel (>=6.29.4,<7.0.0) ; extra == "all" or extra == "dev"
Requires-Dist: isort (>=5.13.2,<6.0.0) ; extra == "all" or extra == "dev"
Requires-Dist: mkdocs-gen-files (>=0.5.0,<0.6.0) ; extra == "all" or extra == "dev"
Requires-Dist: mkdocs-jupyter (>=0.24.7,<0.25.0) ; extra == "all" or extra == "dev"
Requires-Dist: mkdocs-literate-nav (>=0.6.1,<0.7.0) ; extra == "all" or extra == "dev"
Requires-Dist: mkdocs-material (>=9.5.26,<10.0.0) ; extra == "all" or extra == "dev"
Requires-Dist: mkdocs-same-dir (>=0.1.3,<0.2.0) ; extra == "all" or extra == "dev"
Requires-Dist: mkdocs-section-index (>=0.3.9,<0.4.0) ; extra == "all" or extra == "dev"
Requires-Dist: mkdocstrings-python (>=1.10.3,<2.0.0) ; extra == "all" or extra == "dev"
Requires-Dist: ollama (>=0.3.1,<0.4.0) ; extra == "all" or extra == "ollama"
Requires-Dist: openai (>=1.35.3,<2.0.0) ; extra == "all" or extra == "azure-openai" or extra == "openai" or extra == "huggingface-tgi"
Requires-Dist: pandas (>=2.2.3,<3.0.0)
Requires-Dist: pillow (>=10.4.0,<11.0.0) ; extra == "all" or extra == "gemini" or extra == "vertexai" or extra == "azure-openai" or extra == "openai"
Requires-Dist: pre-commit (>=3.7.0,<4.0.0) ; extra == "all" or extra == "dev"
Requires-Dist: pytest (>=8.1.1,<9.0.0) ; extra == "all" or extra == "dev"
Requires-Dist: pytest-asyncio (>=0.23.6,<0.24.0) ; extra == "all" or extra == "dev"
Requires-Dist: pytest-cov (>=5.0.0,<6.0.0) ; extra == "all" or extra == "dev"
Requires-Dist: python-dotenv (>=1.0.1,<2.0.0)
Requires-Dist: quart (>=0.19.6,<0.20.0) ; extra == "all" or extra == "quart"
Requires-Dist: torch (>=2.4.1,<3.0.0) ; extra == "all" or extra == "quart"
Requires-Dist: tqdm (>=4.66.4,<5.0.0)
Requires-Dist: transformers (>=4.44.2,<5.0.0) ; extra == "all" or extra == "quart"
Requires-Dist: vertexai (>=1.66.0,<2.0.0) ; extra == "all" or extra == "gemini" or extra == "vertexai"
